{
  "navigation": [
    { "label": "Software", "link": "/software" },
    { "label": "SAM", "link": "/sam" },
    { "label": "ITSM", "link": "/itsm" },
    { "label": "Einkauf", "link": "/einkauf" },
    { "label": "Consulting", "link": "/consulting" },
    { 
      "label": "Über uns", 
      "link": "/team",
      "children": [
        { "label": "Team", "link": "/team" },
        { "label": "Partner", "link": "/partner" },
        { "label": "Karriere", "link": "/karriere" }
      ]
    }
  ],
  "logo": "/logo.svg",
  "logo_text": "novartum"
}
